query_anon/__init__.py
query_anon/cli.py
query_anon/log_reader.py
query_anon/parser.py
query_anon-0.1.0.dist-info/entry_points.txt
query_anon-0.1.0.dist-info/WHEEL
query_anon-0.1.0.dist-info/METADATA
query_anon-0.1.0.dist-info/RECORD
